pypony.py
src/__init__.py
src/errors.py
src/parsing.py
src/preprocessing.py
src/requests.py
src/steps_schema.yml
src/validate.py
src/verify.py
src/models/__init__.py
src/models/request.py
src/models/response.py
src/models/step.py
tests/__init__.py
tests/integration/__init__.py
tests/unit/__init__.py
tests/unit/test_errors.py
tests/unit/test_parsing.py
tests/unit/test_preprocessing.py
tests/unit/test_requests.py
tests/unit/test_validate.py
tests/unit/test_verify.py
pypony-1.0.0.dist-info/LICENSE
pypony-1.0.0.dist-info/METADATA
pypony-1.0.0.dist-info/WHEEL
pypony-1.0.0.dist-info/entry_points.txt
pypony-1.0.0.dist-info/top_level.txt
pypony-1.0.0.dist-info/RECORD
