Metadata-Version: 2.1
Name: pypony
Version: 1.0.0
Summary: A python utility for contract testing APIs
Home-page: https://github.com/Bandwidth/pypony/
Author: Bandwidth
Author-email: letstalk@bandwidth.com
License: UNKNOWN
Platform: UNKNOWN
License-File: LICENSE
Requires-Dist: attrs (==23.1.0)
Requires-Dist: certifi (==2023.11.17)
Requires-Dist: charset-normalizer (==3.3.2)
Requires-Dist: click (==8.1.7)
Requires-Dist: commonmark (==0.9.1)
Requires-Dist: idna (==3.6)
Requires-Dist: json-ref-dict (==0.7.2)
Requires-Dist: jsonpointer (==2.4)
Requires-Dist: jsonschema (==4.20.0)
Requires-Dist: openapi-schema-validator (==0.6.2)
Requires-Dist: openapi-spec-validator (==0.7.1)
Requires-Dist: pygments (==2.17.2)
Requires-Dist: pyrsistent (==0.20.0)
Requires-Dist: pyyaml (==6.0.1)
Requires-Dist: requests (==2.31.0)
Requires-Dist: rich (==13.7.0)
Requires-Dist: urllib3 (==2.1.0)
Requires-Dist: pathable (==0.4.3) ; python_full_version >= "3.7.0" and python_full_version < "4.0.0"
Requires-Dist: jsonschema-path (==0.3.2) ; python_full_version >= "3.8.0" and python_full_version < "4.0.0"
Requires-Dist: six (==1.16.0) ; python_version >= "2.7" and python_version not in "3.0, 3.1, 3.2, 3.3"
Requires-Dist: rfc3339-validator (==0.1.4) ; python_version >= "2.7" and python_version not in "3.0, 3.1, 3.2, 3.3, 3.4"
Requires-Dist: iniconfig (==2.0.0) ; python_version >= "3.7"
Requires-Dist: mdurl (==0.1.2) ; python_version >= "3.7"
Requires-Dist: packaging (==23.2) ; python_version >= "3.7"
Requires-Dist: jsonschema-specifications (==2023.11.2) ; python_version >= "3.8"
Requires-Dist: lazy-object-proxy (==1.10.0) ; python_version >= "3.8"
Requires-Dist: markdown-it-py (==3.0.0) ; python_version >= "3.8"
Requires-Dist: pluggy (==1.3.0) ; python_version >= "3.8"
Requires-Dist: referencing (==0.31.1) ; python_version >= "3.8"
Requires-Dist: rpds-py (==0.15.2) ; python_version >= "3.8"
